setup.py
djangorestrelationalhyperlink.egg-info/PKG-INFO
djangorestrelationalhyperlink.egg-info/SOURCES.txt
djangorestrelationalhyperlink.egg-info/dependency_links.txt
djangorestrelationalhyperlink.egg-info/requires.txt
djangorestrelationalhyperlink.egg-info/top_level.txt
hyperlinked_relational_serializer/__init__.py
hyperlinked_relational_serializer/models.py
hyperlinked_relational_serializer/serializers.py
hyperlinked_relational_serializer/serializers_copy.py
hyperlinked_relational_serializer/urls.py