Metadata-Version: 1.0
Name: djangorestrelationalhyperlink
Version: 1.2.1
Summary: A hyperlinked serialiser that can can be used to alter relationships via hyperlinks, but otherwise like a hyperlink model serializer
Home-page: https://github.com/fredkingham/django_rest_model_hyperlink_serializers_project
Author: Fred Kingham
Author-email: fredkingham@gmail.com
License: BSD
Platform: UNKNOWN
Classifier: Development Status :: 5 - Production/Stable
Classifier: Environment :: Web Environment
Classifier: Framework :: Django
Classifier: Intended Audience :: Developers
Classifier: License :: OSI Approved :: BSD License
Classifier: Operating System :: OS Independent
Classifier: Programming Language :: Python
Classifier: Programming Language :: Python :: 3
Classifier: Topic :: Internet :: WWW/HTTP
